easy_slack_blocks/__init__.py
easy_slack_blocks/_block_builder/__init__.py
easy_slack_blocks/_block_builder/block_builder.py
easy_slack_blocks/blocks/__init__.py
easy_slack_blocks/blocks/_actions_blocks.py
easy_slack_blocks/blocks/_context_blocks.py
easy_slack_blocks/blocks/_divider_blocks.py
easy_slack_blocks/blocks/_file_blocks.py
easy_slack_blocks/blocks/_header_blocks.py
easy_slack_blocks/blocks/_image_blocks.py
easy_slack_blocks/blocks/_input_blocks.py
easy_slack_blocks/blocks/_section_blocks.py
easy_slack_blocks/components/__init__.py
easy_slack_blocks/components/_block_elements/__init__.py
easy_slack_blocks/components/_block_elements/button.py
easy_slack_blocks/components/_block_elements/checkbox.py
easy_slack_blocks/components/_block_elements/datepicker.py
easy_slack_blocks/components/_block_elements/image.py
easy_slack_blocks/components/_block_elements/multi_select_menu.py
easy_slack_blocks/components/_block_elements/overflow_menu.py
easy_slack_blocks/components/_block_elements/plain_text_input.py
easy_slack_blocks/components/_block_elements/radio_button.py
easy_slack_blocks/components/_block_elements/select_menu.py
easy_slack_blocks/components/_block_elements/time_picker.py
easy_slack_blocks/components/_compositon_objects/__init__.py
easy_slack_blocks/components/_compositon_objects/confirmation.py
easy_slack_blocks/components/_compositon_objects/dispatch_action_configuration.py
easy_slack_blocks/components/_compositon_objects/filter.py
easy_slack_blocks/components/_compositon_objects/option.py
easy_slack_blocks/components/_compositon_objects/option_group.py
easy_slack_blocks/components/_compositon_objects/text.py
easy_slack_blocks-1.0.1.dist-info/LICENSE
easy_slack_blocks-1.0.1.dist-info/METADATA
easy_slack_blocks-1.0.1.dist-info/WHEEL
easy_slack_blocks-1.0.1.dist-info/top_level.txt
easy_slack_blocks-1.0.1.dist-info/RECORD
