Metadata-Version: 2.1
Name: easy-slack-blocks
Version: 1.0.1
Summary: An easy way to format Slack Blocks.
Home-page: https://github.com/matt-cles/easy-slack-blocks/
Author: Matthew Cles
Author-email: matthew@cles.dev
License: MIT
Platform: UNKNOWN
